envlauncher.py
EnvLauncher-0.1a1.dev1.dist-info/LICENSE
EnvLauncher-0.1a1.dev1.dist-info/METADATA
EnvLauncher-0.1a1.dev1.dist-info/WHEEL
EnvLauncher-0.1a1.dev1.dist-info/entry_points.txt
EnvLauncher-0.1a1.dev1.dist-info/top_level.txt
EnvLauncher-0.1a1.dev1.dist-info/RECORD
